{
  "project_info": {
    "project_number": "99461196015",
    "firebase_url": "https://jihuzur-320bb.firebaseio.com",
    "project_id": "jihuzur-320bb",
    "storage_bucket": "jihuzur-320bb.appspot.com"
  },
  "client": [
    {
      "client_info": {
        "mobilesdk_app_id": "1:99461196015:android:2668bc719d6139db",
        "android_client_info": {
          "package_name": "com.example.awizom.jihuzur"
        }
      },
      "oauth_client": [
        {
          "client_id": "99461196015-e9fbd7mnnh57ch36eo2e4fq95upru2r7.apps.googleusercontent.com",
          "client_type": 1,
          "android_info": {
            "package_name": "com.example.awizom.jihuzur",
            "certificate_hash": "393143e9971e7b41ca6a82f0c2ea3f52aea94b74"
          }
        },
        {
          "client_id": "99461196015-taaelg65r6g3b99ropkvbn5jdicidm1a.apps.googleusercontent.com",
          "client_type": 1,
          "android_info": {
            "package_name": "com.example.awizom.jihuzur",
            "certificate_hash": "c295170f9e8e6a7a4036a1625dd5191a47573bc1"
          }
        },
        {
          "client_id": "99461196015-eh8b6mplm5nbn08kvqh4rnufo3divosm.apps.googleusercontent.com",
          "client_type": 3
        }
      ],
      "api_key": [
        {
          "current_key": "AIzaSyAr7-Wz1ey7eVJV5xAuFDcqeTmeEDM4kbc"
        }
      ],
      "services": {
        "analytics_service": {
          "status": 1
        },
        "appinvite_service": {
          "status": 2,
          "other_platform_oauth_client": [
            {
              "client_id": "99461196015-eh8b6mplm5nbn08kvqh4rnufo3divosm.apps.googleusercontent.com",
              "client_type": 3
            }
          ]
        },
        "ads_service": {
          "status": 2
        }
      }
    }
  ],
  "configuration_version": "1"
}